pretix_net_mail/__init__.py
pretix_net_mail/apps.py
pretix_net_mail/renderer.py
pretix_net_mail/signals.py
pretix_net_mail/locale/de/LC_MESSAGES/django.mo
pretix_net_mail/locale/de/LC_MESSAGES/django.po
pretix_net_mail/locale/de_Informal/.gitkeep
pretix_net_mail/locale/de_Informal/LC_MESSAGES/django.mo
pretix_net_mail/locale/de_Informal/LC_MESSAGES/django.po
pretix_net_mail/static/pretix_net_mail/.gitkeep
pretix_net_mail/static/pretix_net_mail/DOSTthumb.png
pretix_net_mail/static/pretix_net_mail/ICINGAthumb.png
pretix_net_mail/static/pretix_net_mail/NETthumb.png
pretix_net_mail/static/pretix_net_mail/OSCAMPthumb.png
pretix_net_mail/static/pretix_net_mail/OSMCthumb.png
pretix_net_mail/static/pretix_net_mail/PROXTALKSthumb.png
pretix_net_mail/static/pretix_net_mail/STACKCONFthumb.png
pretix_net_mail/templates/pretix_net_mail/.gitkeep
pretix_net_mail/templates/pretix_net_mail/DOST.html
pretix_net_mail/templates/pretix_net_mail/ICINGA.html
pretix_net_mail/templates/pretix_net_mail/NES.html
pretix_net_mail/templates/pretix_net_mail/OSCAMP.html
pretix_net_mail/templates/pretix_net_mail/OSMC.html
pretix_net_mail/templates/pretix_net_mail/PROXTALKS.html
pretix_net_mail/templates/pretix_net_mail/STACKCONF.html
pretix_net_mail-1.5.0.dist-info/LICENSE
pretix_net_mail-1.5.0.dist-info/METADATA
pretix_net_mail-1.5.0.dist-info/WHEEL
pretix_net_mail-1.5.0.dist-info/entry_points.txt
pretix_net_mail-1.5.0.dist-info/top_level.txt
pretix_net_mail-1.5.0.dist-info/RECORD
