Metadata-Version: 2.1
Name: pretix-net-mail
Version: 1.5.0
Summary: Custom HTML Email Renderer for NETWAYS
Home-page: https://github.com/NETWAYS/pretix-email-net
Author: NETWAYS GmbH
Author-email: support@netways.de
License: Apache
Platform: UNKNOWN
License-File: LICENSE
